harvester/__init__.py
harvester/ckan_utils.py
harvester/exceptions.py
harvester/harvest.py
harvester/logger_config.py
harvester/utils.py
datagov_harvesting_logic-0.5.0.dist-info/LICENSE.md
datagov_harvesting_logic-0.5.0.dist-info/METADATA
datagov_harvesting_logic-0.5.0.dist-info/WHEEL
datagov_harvesting_logic-0.5.0.dist-info/RECORD
