Metadata-Version: 2.1
Name: datagov-harvesting-logic
Version: 0.5.0
Summary: 
Home-page: https://github.com/GSA/datagov-harvesting-logic
License: LICENSE.md
Author: Datagov Team
Author-email: datagov@gsa.gov
Maintainer: Datagov Team
Maintainer-email: datagov@gsa.gov
Requires-Python: >=3.10
Classifier: License :: Other/Proprietary License
Classifier: Programming Language :: Python :: 3
Classifier: Programming Language :: Python :: 3.10
Classifier: Programming Language :: Python :: 3.11
Classifier: Programming Language :: Python :: 3.12
Requires-Dist: beautifulsoup4 (>=4.12.2,<5.0.0)
Requires-Dist: ckanapi (>=4.7)
Requires-Dist: cloudfoundry-client (>=1.36.0,<2.0.0)
Requires-Dist: deepdiff (>=6)
Requires-Dist: flask (>=3.0.2,<4.0.0)
Requires-Dist: flask-bootstrap (>=3.3.7.1,<4.0.0.0)
Requires-Dist: flask-migrate (>=4.0.7,<5.0.0)
Requires-Dist: flask-sqlalchemy (>=3.1.1,<4.0.0)
Requires-Dist: flask-wtf (>=1.2.1,<2.0.0)
Requires-Dist: jsonschema (>=4)
Requires-Dist: psycopg2-binary (>=2.9.9,<3.0.0)
Requires-Dist: python-dotenv (>=1)
Requires-Dist: sansjson (>=0.3.0,<0.4.0)
Requires-Dist: sqlalchemy (>=2.0.25,<3.0.0)
Project-URL: Repository, https://github.com/GSA/datagov-harvesting-logic
